libcovebods/__init__.py
libcovebods/additionalfields.py
libcovebods/base_task.py
libcovebods/cli.py
libcovebods/config.py
libcovebods/data_reader.py
libcovebods/jsonschemavalidate.py
libcovebods/run_tasks.py
libcovebods/schema.py
libcovebods/schema_dir.py
libcovebods/utils.py
libcovebods/data/schema-0-1-0.json
libcovebods/data/schema-0-2-0.json
libcovebods/data/schema-0-3-0.json
libcovebods/data/schema-0-4-0/codelist-schema.json
libcovebods/data/schema-0-4-0/components.json
libcovebods/data/schema-0-4-0/entity-record.json
libcovebods/data/schema-0-4-0/person-record.json
libcovebods/data/schema-0-4-0/relationship-record.json
libcovebods/data/schema-0-4-0/statement.json
libcovebods/data/schema-0-4-0/codelists/addressType.csv
libcovebods/data/schema-0-4-0/codelists/annotationMotivation.csv
libcovebods/data/schema-0-4-0/codelists/directOrIndirect.csv
libcovebods/data/schema-0-4-0/codelists/entitySubtype.csv
libcovebods/data/schema-0-4-0/codelists/entityType.csv
libcovebods/data/schema-0-4-0/codelists/interestType.csv
libcovebods/data/schema-0-4-0/codelists/nameType.csv
libcovebods/data/schema-0-4-0/codelists/personType.csv
libcovebods/data/schema-0-4-0/codelists/recordStatus.csv
libcovebods/data/schema-0-4-0/codelists/recordType.csv
libcovebods/data/schema-0-4-0/codelists/securitiesIdentifierSchemes.csv
libcovebods/data/schema-0-4-0/codelists/sourceType.csv
libcovebods/data/schema-0-4-0/codelists/unspecifiedReason.csv
libcovebods/tasks/__init__.py
libcovebods/tasks/peps.py
libcovebods/tasks/checks/__init__.py
libcovebods/tasks/checks/legacy_checks.py
libcovebods/tasks/checks/pre_record_checks.py
libcovebods/tasks/checks/record_based_checks.py
libcovebods/tasks/statistics/__init__.py
libcovebods/tasks/statistics/pre_record_statistics.py
libcovebods/tasks/statistics/record_based_statistics.py
tests/__init__.py
tests/api.py
tests/test_additional_checks_0_4_0.py
tests/test_additional_fields_0_4_0.py
tests/test_address_stats.py
tests/test_address_types.py
libcovebods-0.16.0.dist-info/LICENSE
libcovebods-0.16.0.dist-info/METADATA
libcovebods-0.16.0.dist-info/WHEEL
libcovebods-0.16.0.dist-info/entry_points.txt
libcovebods-0.16.0.dist-info/top_level.txt
libcovebods-0.16.0.dist-info/RECORD
